{
    "Entities": [
        {
            "Components": {
                "ID": 16206069851895889868,
                "Mesh": "D:/Repos/MamontEngine/MamontEngine/assets/plane.glb",
                "Tag": "Plane",
                "Transform": {
                    "position": [
                        0.0,
                        0.0,
                        0.0
                    ],
                    "rotation": [
                        0.0,
                        0.0,
                        0.0
                    ],
                    "scale": [
                        2.0,
                        1.0,
                        2.0
                    ]
                }
            }
        },
        {
            "Components": {
                "ID": 13191605861421057313,
                "Mesh": "D:/Repos/MamontEngine/MamontEngine/assets/cylinder.glb",
                "Tag": "Cylinder",
                "Transform": {
                    "position": [
                        1.5,
                        0.699999988079071,
                        0.0
                    ],
                    "rotation": [
                        0.0,
                        0.0,
                        0.0
                    ],
                    "scale": [
                        1.0,
                        1.0,
                        1.0
                    ]
                }
            }
        },
        {
            "Components": {
                "ID": 9292412341627756170,
                "Mesh": "D:/Repos/MamontEngine/MamontEngine/assets/cone.glb",
                "Tag": "Cone",
                "Transform": {
                    "position": [
                        -0.6000000238418579,
                        0.699999988079071,
                        0.0
                    ],
                    "rotation": [
                        0.0,
                        0.0,
                        0.0
                    ],
                    "scale": [
                        1.0,
                        1.0,
                        1.0
                    ]
                }
            }
        },
        {
            "Components": {
                "ID": 16317064349064083454,
                "Mesh": "D:/Repos/MamontEngine/MamontEngine/assets/cube.glb",
                "Tag": "Cube",
                "Transform": {
                    "position": [
                        3.0999999046325684,
                        0.800000011920929,
                        0.0
                    ],
                    "rotation": [
                        0.0,
                        0.0,
                        0.0
                    ],
                    "scale": [
                        1.0,
                        1.0,
                        1.0
                    ]
                }
            }
        }
    ]
}